{
  "meta": {
    "name": "@unhead/shared",
    "dependencies": [
      "@unhead/schema",
      "packrup"
    ],
    "versions": {
      "export-size": "0.5.2",
      "esbuild": "^0.13.8",
      "brotli-size": "^4.0.0"
    }
  },
  "exports": [
    {
      "name": "unpackMeta",
      "path": "dist/index.mjs",
      "minified": 5787,
      "minzipped": 1772,
      "bundled": 9218
    },
    {
      "name": "normaliseEntryTags",
      "path": "dist/index.mjs",
      "minified": 5443,
      "minzipped": 1669,
      "bundled": 7675
    },
    {
      "name": "normaliseTag",
      "path": "dist/index.mjs",
      "minified": 4967,
      "minzipped": 1481,
      "bundled": 6886
    },
    {
      "name": "whitelistSafeInput",
      "path": "dist/index.mjs",
      "minified": 5055,
      "minzipped": 1427,
      "bundled": 7869
    },
    {
      "name": "packMeta",
      "path": "dist/index.mjs",
      "minified": 4468,
      "minzipped": 1399,
      "bundled": 6482
    },
    {
      "name": "processTemplateParams",
      "path": "dist/index.mjs",
      "minified": 4110,
      "minzipped": 1228,
      "bundled": 5418
    },
    {
      "name": "resolvePackedMetaObjectValue",
      "path": "dist/index.mjs",
      "minified": 4190,
      "minzipped": 1209,
      "bundled": 5774
    },
    {
      "name": "normaliseProps",
      "path": "dist/index.mjs",
      "minified": 3876,
      "minzipped": 1095,
      "bundled": 5045
    },
    {
      "name": "tagDedupeKey",
      "path": "dist/index.mjs",
      "minified": 3827,
      "minzipped": 1090,
      "bundled": 4897
    },
    {
      "name": "tagWeight",
      "path": "dist/index.mjs",
      "minified": 3765,
      "minzipped": 1074,
      "bundled": 4925
    },
    {
      "name": "hashTag",
      "path": "dist/index.mjs",
      "minified": 3728,
      "minzipped": 1061,
      "bundled": 4638
    },
    {
      "name": "hashCode",
      "path": "dist/index.mjs",
      "minified": 3572,
      "minzipped": 1001,
      "bundled": 4422
    },
    {
      "name": "normaliseClassProp",
      "path": "dist/index.mjs",
      "minified": 3607,
      "minzipped": 971,
      "bundled": 4478
    },
    {
      "name": "ValidHeadTags",
      "path": "dist/index.mjs",
      "minified": 3540,
      "minzipped": 947,
      "bundled": 4399
    },
    {
      "name": "composableNames",
      "path": "dist/index.mjs",
      "minified": 3534,
      "minzipped": 934,
      "bundled": 4385
    },
    {
      "name": "UniqueTags",
      "path": "dist/index.mjs",
      "minified": 3498,
      "minzipped": 926,
      "bundled": 4322
    },
    {
      "name": "TagConfigKeys",
      "path": "dist/index.mjs",
      "minified": 3503,
      "minzipped": 925,
      "bundled": 4332
    },
    {
      "name": "resolveTitleTemplate",
      "path": "dist/index.mjs",
      "minified": 3489,
      "minzipped": 919,
      "bundled": 4421
    },
    {
      "name": "HasElementTags",
      "path": "dist/index.mjs",
      "minified": 3475,
      "minzipped": 918,
      "bundled": 4321
    },
    {
      "name": "SortModifiers",
      "path": "dist/index.mjs",
      "minified": 3486,
      "minzipped": 917,
      "bundled": 4318
    },
    {
      "name": "TagsWithInnerContent",
      "path": "dist/index.mjs",
      "minified": 3462,
      "minzipped": 914,
      "bundled": 4304
    },
    {
      "name": "TAG_ALIASES",
      "path": "dist/index.mjs",
      "minified": 3459,
      "minzipped": 913,
      "bundled": 4289
    },
    {
      "name": "asArray",
      "path": "dist/index.mjs",
      "minified": 3466,
      "minzipped": 912,
      "bundled": 4303
    },
    {
      "name": "resolveMetaKeyType",
      "path": "dist/index.mjs",
      "minified": 3465,
      "minzipped": 909,
      "bundled": 4322
    },
    {
      "name": "TAG_WEIGHTS",
      "path": "dist/index.mjs",
      "minified": 3448,
      "minzipped": 908,
      "bundled": 4274
    },
    {
      "name": "resolveMetaKeyValue",
      "path": "dist/index.mjs",
      "minified": 3464,
      "minzipped": 906,
      "bundled": 4334
    },
    {
      "name": "SelfClosingTags",
      "path": "dist/index.mjs",
      "minified": 3447,
      "minzipped": 905,
      "bundled": 4278
    },
    {
      "name": "IsBrowser",
      "path": "dist/index.mjs",
      "minified": 3451,
      "minzipped": 901,
      "bundled": 4271
    },
    {
      "name": "TagEntityBits",
      "path": "dist/index.mjs",
      "minified": 3431,
      "minzipped": 895,
      "bundled": 4252
    },
    {
      "name": "defineHeadPlugin",
      "path": "dist/index.mjs",
      "minified": 3445,
      "minzipped": 892,
      "bundled": 4286
    }
  ]
}
