{
  "meta": {
    "name": "@unhead/dom",
    "dependencies": [
      "@unhead/schema",
      "@unhead/shared"
    ],
    "versions": {
      "export-size": "0.5.2",
      "esbuild": "^0.13.8",
      "brotli-size": "^4.0.0"
    }
  },
  "exports": [
    {
      "name": "PatchDomOnEntryUpdatesPlugin",
      "path": "dist/index.mjs",
      "minified": 3310,
      "minzipped": 1408,
      "bundled": 6217
    },
    {
      "name": "debouncedRenderDOMHead",
      "path": "dist/index.mjs",
      "minified": 3020,
      "minzipped": 1306,
      "bundled": 5698
    },
    {
      "name": "renderDOMHead",
      "path": "dist/index.mjs",
      "minified": 2867,
      "minzipped": 1237,
      "bundled": 5317
    },
    {
      "name": "setAttrs",
      "path": "dist/index.mjs",
      "minified": 552,
      "minzipped": 319,
      "bundled": 1118
    },
    {
      "name": "hashTag",
      "path": "dist/index.mjs",
      "minified": 196,
      "minzipped": 142,
      "bundled": 351
    },
    {
      "name": "domUpdatePromise",
      "path": "dist/index.mjs",
      "minified": 50,
      "minzipped": 54,
      "bundled": 196
    }
  ]
}
